Workbook

Sheet Раздел
A1: id | B1: name | C1: desk
A2: 1 | B2: Раздел I. | C2: Живые животные; продукты животного происхождения
A3: 2 | B3: Раздел II. | C3: Продукты растительного происхождения
A4: 3 | B4: Раздел III. | C4: Жиры и масла животного или растительного происхождения и продукты их расщепления; готовые пищевые жиры; воски животного или растительного происхождения
A5: 4 | B5: Раздел IV. | C5: Готовые пищевые продукты; алкогольные и безалкогольные напитки и уксус; табак и его заменители
A6: 5 | B6: Раздел V. | C6: Минеральные продукты
A7: 6 | B7: Раздел VI. | C7: Продукция химической и связанных с ней отраслей промышленности
A8: 7 | B8: Раздел VII. | C8: Пластмассы и изделия из них; каучук, резина и изделия из них
A9: 8 | B9: Раздел VIII. | C9: Hеобработанные шкуры, выделанная кожа, натуральный мех и изделия из них; шорно-седельные изделия и упряжь; дорожные принадлежности, дамские сумки и аналогичные им товары; изделия из кишок животных (кроме волокна из фиброина шелкопряда)
A10: 9 | B10: Раздел IX. | C10: Древесина и изделия из нее; древесный уголь; пробка и изделия из нее; изделия из соломы, альфы или из прочих материалов для плетения; корзиночные и другие плетеные изделия
A11: 10 | B11: Раздел X. | C11: Масса из древесины или из других волокнистых целлюлозных материалов; регенерируемые бумага или картон (макулатура и отходы); бумага, картон и изделия из них
A12: 11 | B12: Раздел XI. | C12: Текстильные материалы и текстильные изделия
A13: 12 | B13: Раздел XII. | C13: Обувь, головные уборы, зонты, солнцезащитные зонты, трости, трости-сиденья, хлысты, кнуты и их части; обработанные перья и изделия из них; искусственные цветы; изделия из человеческого волоса
... A22: 21 | B22: Раздел XXI. | C22: Произведения искусства, предметы коллекционирования и антиквариат

Sheet Группа
A1: id | B1: id_razdel | C1: name
A2: 1 | B2: 1 | C2: Живые животные
A3: 2 | B3: 1 | C3: Мясо и пищевые мясные субпродукты
A4: 3 | B4: 1 | C4: Рыба и ракообразные, моллюски и другие водные беспозвоночные
A5: 4 | B5: 1 | C5: Молочная продукция; яйца птиц; мед натуральный; пищевые продукты животного происхождения, в другом месте не поименованные или не включенные
A6: 5 | B6: 1 | C6: Продукты животного происхождения, в другом месте не поименованные или не включенные
A7: 6 | B7: 2 | C7: Живые деревья и другие растения; луковицы, корни и прочие аналогичные части растений; срезанные цветы и декоративная зелень
A8: 7 | B8: 2 | C8: Овощи и некоторые съедобные корнеплоды и клубнеплоды
A9: 8 | B9: 2 | C9: Съедобные фрукты и орехи; кожура и корки цитрусовых или дынь
A10: 9 | B10: 2 | C10: Кофе, чай, мате, или парагвайский чай, и пряности
A11: 10 | B11: 2 | C11: Злаки
A12: 11 | B12: 2 | C12: Продукция мукомольно-крупяной промышленности; солод; крахмал; инулин; пшеничная клейковина
A13: 12 | B13: 2 | C13: Масличные семена и плоды; прочие семена, плоды и зерно; лекарственные растения и растения для технических целей; солома и фураж
... A97: 97 | B97: 21 | C97: Произведения искусства, предметы коллекционирования и антиквариат

Sheet Позиция
A1: id | B1: id_group | C1: name
A2: 1 | B2: 1 | C2: 0101 Лошади, ослы, мулы и лошаки живые
A3: 2 | B3: 1 | C3: 0102 Крупный рогатый скот живой
A4: 3 | B4: 1 | C4: 0103 Свиньи живые:
A5: 4 | B5: 1 | C5: 0104 Овцы и козы живые:
A6: 5 | B6: 1 | C6: 0105 Домашняя птица живая, то есть куры домашние (Gallus domesticus), утки, гуси, индейки и цесарки:
A7: 6 | B7: 1 | C7: 0106 Живые животные прочие:
A8: 7 | B8: 2 | C8: 0201 Мясо крупного рогатого скота, свежее или охлажденное:
A9: 8 | B9: 2 | C9: 0202 Мясо крупного рогатого скота, замороженное:
A10: 9 | B10: 2 | C10: 0203 Свинина свежая, охлажденная или замороженная:
A11: 10 | B11: 2 | C11: 0204 Баранина или козлятина свежая, охлажденная или замороженная:
A12: 11 | B12: 2 | C12: 0205 Мясо лошадей, ослов, мулов или лошаков, свежее, охлажденное или замороженное:
A13: 12 | B13: 2 | C13: 0206 Пищевые субпродукты крупного рогатого скота, свиней, овец, коз, лошадей, ослов, мулов или лошаков, свежие, охлажденные или замороженные:
... A1001: 996 | B1001: 84 | C1001: 8439 Оборудование для производства массы из волокнистых целлюлозных материалов или для изготовления или отделки бумаги или картона:

Sheet Коды
A1: id_tnved | B1: id_pozition | C1: KodTNVED | D1: Opis | E1: DopEd | F1: im_date_update_tnved
A2: 100 | C2: 0101 | D2: Лошади, ослы, мулы и лошаки живые: | F2: 28.08.2020
A3: 200 | D3: - лошади: | F3: 28.08.2020
A4: 300 | C4: 0101 21 000 0 | D4: -- чистопородные племенные животные | E4: шт | F4: 28.08.2020
A5: 400 | C5: 0101 29 | D5: -- прочие: | F5: 28.08.2020
A6: 500 | C6: 0101 29 100 0 | D6: --- убойные | E6: шт | F6: 28.08.2020
A7: 600 | C7: 0101 29 900 0 | D7: --- прочие | E7: шт | F7: 28.08.2020
A8: 700 | C8: 0101 30 000 0 | D8: - ослы | E8: шт | F8: 28.08.2020
A9: 800 | C9: 0101 90 000 0 | D9: - прочие | E9: шт | F9: 28.08.2020
A10: 900 | C10: 0102 | D10: Крупный рогатый скот живой: | F10: 28.08.2020
A11: 1000 | D11: - домашний крупный рогатый скот: | F11: 28.08.2020
A12: 1100 | C12: 0102 21 | D12: -- чистопородные племенные животные: | F12: 28.08.2020
A13: 1200 | C13: 0102 21 100 0 | D13: --- нетели (самки крупного рогатого скота до первого отела) | E13: шт | F13: 28.08.2020
A14: 1300 | C14: 0102 21 300 0 | D14: --- коровы | E14: шт | F14: 28.08.2020
A15: 1400 | C15: 0102 21 900 0 | D15: --- прочие | E15: шт | F15: 28.08.2020
A16: 1500 | C16: 0102 29 | D16: -- прочие: | F16: 28.08.2020
A17: 1600 | C17: 0102 29 050 0 | D17: --- подрода Bibos или подрода Poephagus | E17: шт | F17: 28.08.2020
A18: 1700 | D18: --- прочие: | F18: 28.08.2020
A19: 1800 | C19: 0102 29 100 0 | D19: ---- массой не более 80 кг | E19: шт | F19: 28.08.2020
A20: 1900 | D20: ---- массой более 80 кг, но не более 160 кг: | F20: 28.08.2020
A21: 2000 | C21: 0102 29 210 0 | D21: ----- убойные | E21: шт | F21: 28.08.2020
A22: 2100 | C22: 0102 29 290 0 | D22: ----- прочие | E22: шт | F22: 28.08.2020
A23: 2200 | D23: ---- массой более 160 кг, но не более 300 кг: | F23: 28.08.2020
A24: 2300 | C24: 0102 29 410 0 | D24: ----- убойные | E24: шт | F24: 28.08.2020
A25: 2400 | C25: 0102 29 490 0 | D25: ----- прочие | E25: шт | F25: 28.08.2020
A26: 2500 | D26: ---- массой более 300 кг: | F26: 28.08.2020
A27: 2600 | D27: ----- нетели (самки крупного рогатого скота до первого отела): | F27: 28.08.2020
A28: 2700 | C28: 0102 29 510 0 | D28: ------ убойные | E28: шт | F28: 28.08.2020
A29: 2800 | C29: 0102 29 590 0 | D29: ------ прочие | E29: шт | F29: 28.08.2020
A30: 2900 | D30: ----- коровы: | F30: 28.08.2020
A31: 3000 | C31: 0102 29 610 0 | D31: ------ убойные | E31: шт | F31: 28.08.2020
A32: 3100 | C32: 0102 29 690 0 | D32: ------ прочие | E32: шт | F32: 28.08.2020
A33: 3200 | D33: ----- прочие: | F33: 28.08.2020
A34: 3300 | C34: 0102 29 910 0 | D34: ------ убойные | E34: шт | F34: 28.08.2020
A35: 3400 | C35: 0102 29 990 0 | D35: ------ прочие | E35: шт | F35: 28.08.2020
A36: 3500 | D36: - буйволы: | F36: 28.08.2020
A37: 3600 | C37: 0102 31 000 0 | D37: -- чистопородные племенные животные | E37: шт | F37: 28.08.2020
A38: 3700 | C38: 0102 39 | D38: -- прочие: | F38: 28.08.2020
A39: 3800 | C39: 0102 39 100 0 | D39: --- домашние виды | E39: шт | F39: 28.08.2020
A40: 3900 | C40: 0102 39 900 0 | D40: --- прочие | E40: шт | F40: 28.08.2020
A41: 4000 | C41: 0102 90 | D41: - прочие: | F41: 28.08.2020
A42: 4100 | C42: 0102 90 200 0 | D42: -- чистопородные племенные животные | E42: шт | F42: 28.08.2020
A43: 4200 | D43: -- прочие: | F43: 28.08.2020
A44: 4300 | C44: 0102 90 910 0 | D44: --- домашние виды | E44: шт | F44: 28.08.2020
A45: 4400 | C45: 0102 90 990 0 | D45: --- прочие | E45: шт | F45: 28.08.2020
A46: 4500 | C46: 0103 | D46: Свиньи живые: | F46: 28.08.2020
A47: 4600 | C47: 0103 10 000 0 | D47: - чистопородные племенные животные | E47: шт | F47: 28.08.2020
A48: 4700 | D48: - прочие: | F48: 28.08.2020
A49: 4800 | C49: 0103 91 | D49: -- массой менее 50 кг: | F49: 28.08.2020
A50: 4900 | C50: 0103 91 100 0 | D50: --- домашние виды | E50: шт | F50: 28.08.2020
A51: 5000 | C51: 0103 91 900 0 | D51: --- прочие | E51: шт | F51: 28.08.2020
A52: 5100 | C52: 0103 92 | D52: -- массой 50 кг или более: | F52: 28.08.2020
A53: 5200 | D53: --- домашние виды: | F53: 28.08.2020
A54: 5300 | C54: 0103 92 110 0 | D54: ---- свиноматки массой не менее 160 кг, имевшие по крайней мере один опорос | E54: шт | F54: 28.08.2020
A55: 5400 | C55: 0103 92 190 0 | D55: ---- прочие | E55: шт | F55: 28.08.2020
A56: 5500 | C56: 0103 92 900 0 | D56: --- прочие | E56: шт | F56: 28.08.2020
A57: 5600 | C57: 0104 | D57: Овцы и козы живые: | F57: 28.08.2020
A58: 5700 | C58: 0104 10 | D58: - овцы: | F58: 28.08.2020
A59: 5800 | C59: 0104 10 100 0 | D59: -- чистопородные племенные животные | E59: шт | F59: 28.08.2020
A60: 5900 | D60: -- прочие: | F60: 28.08.2020
A61: 6000 | C61: 0104 10 300 0 | D61: --- ягнята (до одного года) | E61: шт | F61: 28.08.2020
A62: 6100 | C62: 0104 10 800 0 | D62: --- прочие | E62: шт | F62: 28.08.2020
A63: 6200 | C63: 0104 20 | D63: - козы: | F63: 28.08.2020
A64: 6300 | C64: 0104 20 100 0 | D64: -- чистопородные племенные животные | E64: шт | F64: 28.08.2020
A65: 6400 | C65: 0104 20 900 0 | D65: -- прочие | E65: шт | F65: 28.08.2020
A66: 6500 | C66: 0105 | D66: Домашняя птица живая, то есть куры домашние (Gallus domesticus), утки, гуси, индейки и цесарки: | F66: 28.08.2020
A67: 6600 | D67: - массой не более 185 г: | F67: 28.08.2020
A68: 6700 | C68: 0105 11 | D68: -- куры домашние (Gallus domesticus): | F68: 28.08.2020
A69: 6800 | D69: --- цыплята прародительских и материнских линий племенного разведения: | F69: 28.08.2020
A70: 6900 | C70: 0105 11 110 0 | D70: ---- линии несушек | E70: шт | F70: 28.08.2020
A71: 7000 | C71: 0105 11 190 0 | D71: ---- прочие | E71: шт | F71: 28.08.2020
A72: 7100 | D72: --- прочие: | F72: 28.08.2020
A73: 7200 | C73: 0105 11 910 0 | D73: ---- линии несушек | E73: шт | F73: 28.08.2020
A74: 7300 | C74: 0105 11 990 0 | D74: ---- прочие | E74: шт | F74: 28.08.2020
A75: 7400 | C75: 0105 12 000 0 | D75: -- индейки | E75: шт | F75: 28.08.2020
A76: 7500 | C76: 0105 13 000 0 | D76: -- утки | E76: шт | F76: 28.08.2020
A77: 7600 | C77: 0105 14 000 0 | D77: -- гуси | E77: шт | F77: 28.08.2020
A78: 7700 | C78: 0105 15 000 0 | D78: -- цесарки | E78: шт | F78: 28.08.2020
A79: 7800 | D79: - прочие: | F79: 28.08.2020
A80: 7900 | C80: 0105 94 000 0 | D80: -- куры домашние (Gallus domesticus) | E80: шт | F80: 28.08.2020
A81: 8000 | C81: 0105 99 | D81: -- прочие: | F81: 28.08.2020
A82: 8100 | C82: 0105 99 100 0 | D82: --- утки | E82: шт | F82: 28.08.2020
A83: 8200 | C83: 0105 99 200 0 | D83: --- гуси | E83: шт | F83: 28.08.2020
A84: 8300 | C84: 0105 99 300 0 | D84: --- индейки | E84: шт | F84: 28.08.2020
A85: 8400 | C85: 0105 99 500 0 | D85: --- цесарки | E85: шт | F85: 28.08.2020
A86: 8500 | C86: 0106 | D86: Живые животные прочие: | F86: 28.08.2020
A87: 8600 | D87: - млекопитающие: | F87: 28.08.2020
A88: 8700 | C88: 0106 11 00 | D88: -- приматы: | F88: 28.08.2020
A89: 8800 | C89: 0106 11 001 0 | D89: --- для научно-исследовательских целей | E89: шт | F89: 28.08.2020
A90: 8900 | C90: 0106 11 009 0 | D90: --- прочие | E90: шт | F90: 28.08.2020
A91: 9000 | C91: 0106 12 00 | D91: -- киты, дельфины и морские свиньи (млекопитающие отряда Cetacea); ламантины и дюгони (млекопитающие отряда Sirenia); тюлени, морские львы и моржи (млекопитающие подотряда Pinnipedia): | F91: 28.08.2020
A92: 9100 | C92: 0106 12 001 0 | D92: --- для научно-исследовательских целей | E92: шт | F92: 28.08.2020
A93: 9200 | C93: 0106 12 009 0 | D93: --- прочие | E93: шт | F93: 28.08.2020
A94: 9300 | C94: 0106 13 00 | D94: -- верблюды и прочие животные семейства верблюдовых (Camelidae): | F94: 28.08.2020
A95: 9400 | C95: 0106 13 001 0 | D95: --- для научно-исследовательских целей | E95: шт | F95: 28.08.2020
A96: 9500 | C96: 0106 13 009 0 | D96: --- прочие | E96: шт | F96: 28.08.2020
A97: 9600 | C97: 0106 14 | D97: -- кролики и зайцы: | F97: 28.08.2020
A98: 9700 | C98: 0106 14 10 | D98: --- кролики домашние: | F98: 28.08.2020
A99: 9800 | C99: 0106 14 101 0 | D99: ---- для научно-исследовательских целей | E99: шт | F99: 28.08.2020
A100: 9900 | C100: 0106 14 109 0 | D100: ---- прочие | E100: шт | F100: 28.08.2020
...

Sheet Пошлина_импорт
A1: id_tnved | B1: im_poshlin | C1: date_start | D1: date_end | E1: Код пошлины | F1: id_tnved_в наличии
A2: 300 | B2: 0 | C2: 28.08.2020 | E2: =INDEX(Коды!A2:C19627,MATCH(A2,Коды!A2:A19627,0),3) -> 0101 21 000 0 | F2: =COUNTIF(Коды!A2:A19627,A2) -> 1
A3: 500 | B3: 5 | C3: 28.08.2020 | E3: =INDEX(Коды!A3:C19628,MATCH(A3,Коды!A3:A19628,0),3) -> 0101 29 100 0 | F3: =COUNTIF(Коды!A3:A19628,A3) -> 1
A4: 600 | B4: 5 | C4: 28.08.2020 | E4: =INDEX(Коды!A4:C19629,MATCH(A4,Коды!A4:A19629,0),3) -> 0101 29 900 0 | F4: =COUNTIF(Коды!A4:A19629,A4) -> 1
A5: 700 | B5: 5 | C5: 28.08.2020 | E5: =INDEX(Коды!A5:C19630,MATCH(A5,Коды!A5:A19630,0),3) -> 0101 30 000 0 | F5: =COUNTIF(Коды!A5:A19630,A5) -> 1
A6: 800 | B6: 5 | C6: 28.08.2020 | E6: =INDEX(Коды!A6:C19631,MATCH(A6,Коды!A6:A19631,0),3) -> 0101 90 000 0 | F6: =COUNTIF(Коды!A6:A19631,A6) -> 1
A7: 1200 | B7: 0 | C7: 28.08.2020 | E7: =INDEX(Коды!A7:C19632,MATCH(A7,Коды!A7:A19632,0),3) -> 0102 21 100 0 | F7: =COUNTIF(Коды!A7:A19632,A7) -> 1
A8: 1300 | B8: 0 | C8: 28.08.2020 | E8: =INDEX(Коды!A8:C19633,MATCH(A8,Коды!A8:A19633,0),3) -> 0102 21 300 0 | F8: =COUNTIF(Коды!A8:A19633,A8) -> 1
A9: 1400 | B9: 0 | C9: 28.08.2020 | E9: =INDEX(Коды!A9:C19634,MATCH(A9,Коды!A9:A19634,0),3) -> 0102 21 900 0 | F9: =COUNTIF(Коды!A9:A19634,A9) -> 1
A10: 1600 | B10: 5 | C10: 28.08.2020 | E10: =INDEX(Коды!A10:C19635,MATCH(A10,Коды!A10:A19635,0),3) -> 0102 29 050 0 | F10: =COUNTIF(Коды!A10:A19635,A10) -> 1
A11: 1800 | B11: 5 | C11: 28.08.2020 | E11: =INDEX(Коды!A11:C19636,MATCH(A11,Коды!A11:A19636,0),3) -> 0102 29 100 0 | F11: =COUNTIF(Коды!A11:A19636,A11) -> 1
A12: 2000 | B12: 5 | C12: 28.08.2020 | E12: =INDEX(Коды!A12:C19637,MATCH(A12,Коды!A12:A19637,0),3) -> 0102 29 210 0 | F12: =COUNTIF(Коды!A12:A19637,A12) -> 1
A13: 2100 | B13: 5 | C13: 28.08.2020 | E13: =INDEX(Коды!A13:C19638,MATCH(A13,Коды!A13:A19638,0),3) -> 0102 29 290 0 | F13: =COUNTIF(Коды!A13:A19638,A13) -> 1
... A12298: 1962600 | B12298: 0 | C12298: 28.08.2020 | E12298: =INDEX(Коды!A12298:C31923,MATCH(A12298,Коды!A12298:A31923,0),3) -> 9706 00 000 0 | F12298: =COUNTIF(Коды!A12298:A31923,A12298) -> 1

Sheet Пошлина_экспорт
A1: id_tnved | B1: ex_poshlin | C1: date_start | D1: date_end | E1: Код пошлины | F1: id_tnved_в наличии
E2: =INDEX(Коды!A2:C19627,MATCH(A2,Коды!A2:A19627,0),3) -> #N/A | F2: =COUNTIF(Коды!A2:A19627,A2) -> 0

Sheet Акциз
A1: id_tnved | B1: actsiz_disc | C1: actsiz_phlin | D1: actsiz_disc_dop | E1: date_start | F1: date_end | G1: Код пошлины | H1: id_tnved_в наличии
G2: =INDEX(Коды!C2:E19627,MATCH(C2,Коды!C2:C19627,0),3) -> #N/A | H2: =COUNTIF(Коды!C2:C19627,A2) -> 0
